nrpys-0.1.1.dist-info/METADATA
nrpys-0.1.1.dist-info/WHEEL
nrpys-0.1.1.dist-info/license_files/LICENSE.txt
nrpys/__init__.py
nrpys/py.typed
nrpys/nrpys.pyi
nrpys/nrpys.cpython-39-darwin.so
nrpys-0.1.1.dist-info/RECORD
