Metadata-Version: 2.1
Name: nrpys
Version: 0.1.1
Classifier: Programming Language :: Rust
Classifier: Programming Language :: Python :: Implementation :: CPython
Classifier: Programming Language :: Python :: Implementation :: PyPy
License-File: LICENSE.txt
Author: Kai Blin <kblin@biosustain.dtu.dk>
Author-email: Kai Blin <kblin@biosustain.dtu.dk>
License: AGPL-3.0-or-later
Requires-Python: >=3.7
Project-URL: Source Code, https://github.com/kblin/nrpys.git
